{
  "head": {
    "vars": [ "author" ]
  } ,
  "results": {
    "bindings": [
      {
        "author": { "type": "uri" , "value": "http://www.connaissance.io/onto/biblio/bibliographica#Quincy_Troupe" }
      } ,
      {
        "author": { "type": "uri" , "value": "http://www.connaissance.io/onto/biblio/bibliographica#Ladies_Union_Circle" }
      } ,
      {
        "author": { "type": "uri" , "value": "http://www.connaissance.io/onto/biblio/bibliographica#T_Coraghessan_Boyle" }
      } ,
      {
        "author": { "type": "uri" , "value": "http://www.connaissance.io/onto/biblio/bibliographica#Alan_Watts" }
      } ,
      {
        "author": { "type": "uri" , "value": "http://www.connaissance.io/onto/biblio/bibliographica#Andrea_Barrett" }
      } ,
      {
        "author": { "type": "uri" , "value": "http://www.connaissance.io/onto/biblio/bibliographica#Michael_Crichton" }
      } ,
      {
        "author": { "type": "uri" , "value": "http://www.connaissance.io/onto/biblio/bibliographica#Craig_Claiborne" }
      } ,
      {
        "author": { "type": "uri" , "value": "http://www.connaissance.io/onto/biblio/bibliographica#Octavia_E_Butler" }
      } ,
      {
        "author": { "type": "uri" , "value": "http://www.connaissance.io/onto/biblio/bibliographica#Scott_Simon" }
      } ,
      {
        "author": { "type": "uri" , "value": "http://www.connaissance.io/onto/biblio/bibliographica#AA_Milne" }
      } ,
      {
        "author": { "type": "uri" , "value": "http://www.connaissance.io/onto/biblio/bibliographica#Anne_Cameron" }
      } ,
      {
        "author": { "type": "uri" , "value": "http://www.connaissance.io/onto/biblio/bibliographica#John_Watkinson" }
      } ,
      {
        "author": { "type": "uri" , "value": "http://www.connaissance.io/onto/biblio/bibliographica#Barry_Galbraith" }
      } ,
      {
        "author": { "type": "uri" , "value": "http://www.connaissance.io/onto/biblio/bibliographica#Edwidge_Danticat" }
      } ,
      {
        "author": { "type": "uri" , "value": "http://www.connaissance.io/onto/biblio/bibliographica#Isabel_Allende" }
      } ,
      {
        "author": { "type": "uri" , "value": "http://www.connaissance.io/onto/biblio/bibliographica#Charles_Frazier" }
      } ,
      {
        "author": { "type": "uri" , "value": "http://www.connaissance.io/onto/biblio/bibliographica#Mort_Rosenblum" }
      } ,
      {
        "author": { "type": "uri" , "value": "http://www.connaissance.io/onto/biblio/bibliographica#Richard_Nelson" }
      } ,
      {
        "author": { "type": "uri" , "value": "http://www.connaissance.io/onto/biblio/bibliographica#Graeme_Base" }
      } ,
      {
        "author": { "type": "uri" , "value": "http://www.connaissance.io/onto/biblio/bibliographica#Dr_Seuss" }
      } ,
      {
        "author": { "type": "uri" , "value": "http://www.connaissance.io/onto/biblio/bibliographica#Steven_Nightingale" }
      } ,
      {
        "author": { "type": "uri" , "value": "http://www.connaissance.io/onto/biblio/bibliographica#Richard_Flanagan" }
      } ,
      {
        "author": { "type": "uri" , "value": "http://www.connaissance.io/onto/biblio/bibliographica#Alifair_Burke" }
      } ,
      {
        "author": { "type": "uri" , "value": "http://www.connaissance.io/onto/biblio/bibliographica#Julee_Rosso" }
      } ,
      {
        "author": { "type": "uri" , "value": "http://www.connaissance.io/onto/biblio/bibliographica#DeLorme_Mapping_Company" }
      } ,
      {
        "author": { "type": "uri" , "value": "http://www.connaissance.io/onto/biblio/bibliographica#Rolling_Stone" }
      } ,
      {
        "author": { "type": "uri" , "value": "http://www.connaissance.io/onto/biblio/bibliographica#Clive_Cussler" }
      } ,
      {
        "author": { "type": "uri" , "value": "http://www.connaissance.io/onto/biblio/bibliographica#Judy_Fong_Bates" }
      } ,
      {
        "author": { "type": "uri" , "value": "http://www.connaissance.io/onto/biblio/bibliographica#Patricia_Henley" }
      } ,
      {
        "author": { "type": "uri" , "value": "http://www.connaissance.io/onto/biblio/bibliographica#Wendy_Esko" }
      } ,
      {
        "author": { "type": "uri" , "value": "http://www.connaissance.io/onto/biblio/bibliographica#Jack_Kerouac" }
      } ,
      {
        "author": { "type": "uri" , "value": "http://www.connaissance.io/onto/biblio/bibliographica#Stephen_Hunt" }
      } ,
      {
        "author": { "type": "uri" , "value": "http://www.connaissance.io/onto/biblio/bibliographica#Toni_Morrison" }
      } ,
      {
        "author": { "type": "uri" , "value": "http://www.connaissance.io/onto/biblio/bibliographica#Bruno_Nettl" }
      } ,
      {
        "author": { "type": "uri" , "value": "http://www.connaissance.io/onto/biblio/bibliographica#David_Rains_Wallace" }
      } ,
      {
        "author": { "type": "uri" , "value": "http://www.connaissance.io/onto/biblio/bibliographica#Patricia_Cornwell" }
      } ,
      {
        "author": { "type": "uri" , "value": "http://www.connaissance.io/onto/biblio/bibliographica#Emily_Dodi" }
      } ,
      {
        "author": { "type": "uri" , "value": "http://www.connaissance.io/onto/biblio/bibliographica#Dermot_Bolger" }
      } ,
      {
        "author": { "type": "uri" , "value": "http://www.connaissance.io/onto/biblio/bibliographica#Jean_Smith" }
      } ,
      {
        "author": { "type": "uri" , "value": "http://www.connaissance.io/onto/biblio/bibliographica#Stuart_Woods" }
      } ,
      {
        "author": { "type": "uri" , "value": "http://www.connaissance.io/onto/biblio/bibliographica#Andrea_Dodi" }
      } ,
      {
        "author": { "type": "uri" , "value": "http://www.connaissance.io/onto/biblio/bibliographica#Anthony_Bourdain" }
      } ,
      {
        "author": { "type": "uri" , "value": "http://www.connaissance.io/onto/biblio/bibliographica#Keith_Jack" }
      } ,
      {
        "author": { "type": "uri" , "value": "http://www.connaissance.io/onto/biblio/bibliographica#John_Klemmer" }
      } ,
      {
        "author": { "type": "uri" , "value": "http://www.connaissance.io/onto/biblio/bibliographica#Arthur_Winfield_Knight" }
      } ,
      {
        "author": { "type": "uri" , "value": "http://www.connaissance.io/onto/biblio/bibliographica#AJ_Verdelle" }
      } ,
      {
        "author": { "type": "uri" , "value": "http://www.connaissance.io/onto/biblio/bibliographica#John_Clellon_Holmes" }
      } ,
      {
        "author": { "type": "uri" , "value": "http://www.connaissance.io/onto/biblio/bibliographica#Steven_Rinella" }
      } ,
      {
        "author": { "type": "uri" , "value": "http://www.connaissance.io/onto/biblio/bibliographica#Toyoaki_Kawai" }
      } ,
      {
        "author": { "type": "uri" , "value": "http://www.connaissance.io/onto/biblio/bibliographica#Dany_Laferriere" }
      } ,
      {
        "author": { "type": "uri" , "value": "http://www.connaissance.io/onto/biblio/bibliographica#Tina_McElroy_Ansa" }
      } ,
      {
        "author": { "type": "uri" , "value": "http://www.connaissance.io/onto/biblio/bibliographica#Paul_Bosland" }
      } ,
      {
        "author": { "type": "uri" , "value": "http://www.connaissance.io/onto/biblio/bibliographica#Relix_Magazine" }
      } ,
      {
        "author": { "type": "uri" , "value": "http://www.connaissance.io/onto/biblio/bibliographica#Bob_Dylan" }
      } ,
      {
        "author": { "type": "uri" , "value": "http://www.connaissance.io/onto/biblio/bibliographica#Bryan_Thomas" }
      } ,
      {
        "author": { "type": "uri" , "value": "http://www.connaissance.io/onto/biblio/bibliographica#John_McPhee" }
      } ,
      {
        "author": { "type": "uri" , "value": "http://www.connaissance.io/onto/biblio/bibliographica#Lee_Child" }
      } ,
      {
        "author": { "type": "uri" , "value": "http://www.connaissance.io/onto/biblio/bibliographica#Jon_Hassler" }
      } ,
      {
        "author": { "type": "uri" , "value": "http://www.connaissance.io/onto/biblio/bibliographica#Michael_Ondaatje" }
      } ,
      {
        "author": { "type": "uri" , "value": "http://www.connaissance.io/onto/biblio/bibliographica#Krystyna_Pomorska" }
      } ,
      {
        "author": { "type": "uri" , "value": "http://www.connaissance.io/onto/biblio/bibliographica#Phil_Lesh" }
      } ,
      {
        "author": { "type": "uri" , "value": "http://www.connaissance.io/onto/biblio/bibliographica#Thomas_Sanchez" }
      } ,
      {
        "author": { "type": "uri" , "value": "http://www.connaissance.io/onto/biblio/bibliographica#Lewis_Carroll" }
      } ,
      {
        "author": { "type": "uri" , "value": "http://www.connaissance.io/onto/biblio/bibliographica#Thomas_Pynchon" }
      } ,
      {
        "author": { "type": "uri" , "value": "http://www.connaissance.io/onto/biblio/bibliographica#Pablo_Neruda" }
      } ,
      {
        "author": { "type": "uri" , "value": "http://www.connaissance.io/onto/biblio/bibliographica#Peter_Mayle" }
      } ,
      {
        "author": { "type": "uri" , "value": "http://www.connaissance.io/onto/biblio/bibliographica#John_Kennedy_Toole" }
      } ,
      {
        "author": { "type": "uri" , "value": "http://www.connaissance.io/onto/biblio/bibliographica#Ernest_Callenbach" }
      } ,
      {
        "author": { "type": "uri" , "value": "http://www.connaissance.io/onto/biblio/bibliographica#Elmore_Leonard" }
      } ,
      {
        "author": { "type": "uri" , "value": "http://www.connaissance.io/onto/biblio/bibliographica#Howard_Wallach" }
      } ,
      {
        "author": { "type": "uri" , "value": "http://www.connaissance.io/onto/biblio/bibliographica#Sarah_Bird" }
      } ,
      {
        "author": { "type": "uri" , "value": "http://www.connaissance.io/onto/biblio/bibliographica#Maya_Angelou" }
      } ,
      {
        "author": { "type": "uri" , "value": "http://www.connaissance.io/onto/biblio/bibliographica#Marianne_Fredriksson" }
      } ,
      {
        "author": { "type": "uri" , "value": "http://www.connaissance.io/onto/biblio/bibliographica#Gino_Sky" }
      } ,
      {
        "author": { "type": "uri" , "value": "http://www.connaissance.io/onto/biblio/bibliographica#David_Guterson" }
      } ,
      {
        "author": { "type": "uri" , "value": "http://www.connaissance.io/onto/biblio/bibliographica#AS_Byatt" }
      } ,
      {
        "author": { "type": "uri" , "value": "http://www.connaissance.io/onto/biblio/bibliographica#Bradford_Morrow" }
      } ,
      {
        "author": { "type": "uri" , "value": "http://www.connaissance.io/onto/biblio/bibliographica#A_Vogel" }
      } ,
      {
        "author": { "type": "uri" , "value": "http://www.connaissance.io/onto/biblio/bibliographica#Ann_Patchett" }
      } ,
      {
        "author": { "type": "uri" , "value": "http://www.connaissance.io/onto/biblio/bibliographica#Arturo_Perez_Reverte" }
      } ,
      {
        "author": { "type": "uri" , "value": "http://www.connaissance.io/onto/biblio/bibliographica#Gloria_Naylor" }
      } ,
      {
        "author": { "type": "uri" , "value": "http://www.connaissance.io/onto/biblio/bibliographica#Daniel_Mathews" }
      } ,
      {
        "author": { "type": "uri" , "value": "http://www.connaissance.io/onto/biblio/bibliographica#Anita_Shreve" }
      } ,
      {
        "author": { "type": "uri" , "value": "http://www.connaissance.io/onto/biblio/bibliographica#Jim_Harrison" }
      } ,
      {
        "author": { "type": "uri" , "value": "http://www.connaissance.io/onto/biblio/bibliographica#William_Trevor" }
      } ,
      {
        "author": { "type": "uri" , "value": "http://www.connaissance.io/onto/biblio/bibliographica#Barry_Lopez" }
      } ,
      {
        "author": { "type": "uri" , "value": "http://www.connaissance.io/onto/biblio/bibliographica#Rotraud_Michael-Degner" }
      } ,
      {
        "author": { "type": "uri" , "value": "http://www.connaissance.io/onto/biblio/bibliographica#John_Straley" }
      } ,
      {
        "author": { "type": "uri" , "value": "http://www.connaissance.io/onto/biblio/bibliographica#Wendy_Holden" }
      } ,
      {
        "author": { "type": "uri" , "value": "http://www.connaissance.io/onto/biblio/bibliographica#Elisabeth_Hyde" }
      } ,
      {
        "author": { "type": "uri" , "value": "http://www.connaissance.io/onto/biblio/bibliographica#Ann_Dunnigan" }
      } ,
      {
        "author": { "type": "uri" , "value": "http://www.connaissance.io/onto/biblio/bibliographica#Tim_Sandlin" }
      } ,
      {
        "author": { "type": "uri" , "value": "http://www.connaissance.io/onto/biblio/bibliographica#Paul_Reps" }
      } ,
      {
        "author": { "type": "uri" , "value": "http://www.connaissance.io/onto/biblio/bibliographica#Andre_Dubus" }
      } ,
      {
        "author": { "type": "uri" , "value": "http://www.connaissance.io/onto/biblio/bibliographica#Helene_Tursten" }
      } ,
      {
        "author": { "type": "uri" , "value": "http://www.connaissance.io/onto/biblio/bibliographica#Robert_Michael_Pyle" }
      } ,
      {
        "author": { "type": "uri" , "value": "http://www.connaissance.io/onto/biblio/bibliographica#Philip_Kapleau" }
      } ,
      {
        "author": { "type": "uri" , "value": "http://www.connaissance.io/onto/biblio/bibliographica#Tim_OBrien" }
      } ,
      {
        "author": { "type": "uri" , "value": "http://www.connaissance.io/onto/biblio/bibliographica#Rex_Pickett" }
      } ,
      {
        "author": { "type": "uri" , "value": "http://www.connaissance.io/onto/biblio/bibliographica#Bill_Griffith" }
      } ,
      {
        "author": { "type": "uri" , "value": "http://www.connaissance.io/onto/biblio/bibliographica#Adelle_Davis" }
      } ,
      {
        "author": { "type": "uri" , "value": "http://www.connaissance.io/onto/biblio/bibliographica#Frank_MacEowen" }
      } ,
      {
        "author": { "type": "uri" , "value": "http://www.connaissance.io/onto/biblio/bibliographica#Ana_Castillo" }
      } ,
      {
        "author": { "type": "uri" , "value": "http://www.connaissance.io/onto/biblio/bibliographica#Peter_Høeg" }
      } ,
      {
        "author": { "type": "uri" , "value": "http://www.connaissance.io/onto/biblio/bibliographica#Robert_Ludlum" }
      } ,
      {
        "author": { "type": "uri" , "value": "http://www.connaissance.io/onto/biblio/bibliographica#Thomas_McGuane" }
      } ,
      {
        "author": { "type": "uri" , "value": "http://www.connaissance.io/onto/biblio/bibliographica#Kwadwo_Agymah_Kamau" }
      } ,
      {
        "author": { "type": "uri" , "value": "http://www.connaissance.io/onto/biblio/bibliographica#Edward_Abbey" }
      } ,
      {
        "author": { "type": "uri" , "value": "http://www.connaissance.io/onto/biblio/bibliographica#Mark_Jacobs" }
      } ,
      {
        "author": { "type": "uri" , "value": "http://www.connaissance.io/onto/biblio/bibliographica#John_Barth" }
      } ,
      {
        "author": { "type": "uri" , "value": "http://www.connaissance.io/onto/biblio/bibliographica#Betty_Wason" }
      } ,
      {
        "author": { "type": "uri" , "value": "http://www.connaissance.io/onto/biblio/bibliographica#Michael_Scott" }
      } ,
      {
        "author": { "type": "uri" , "value": "http://www.connaissance.io/onto/biblio/bibliographica#Sheila_Lukins" }
      } ,
      {
        "author": { "type": "uri" , "value": "http://www.connaissance.io/onto/biblio/bibliographica#Tom_Robbins" }
      } ,
      {
        "author": { "type": "uri" , "value": "http://www.connaissance.io/onto/biblio/bibliographica#Bob_Marley" }
      } ,
      {
        "author": { "type": "uri" , "value": "http://www.connaissance.io/onto/biblio/bibliographica#Ken_Kesey" }
      } ,
      {
        "author": { "type": "uri" , "value": "http://www.connaissance.io/onto/biblio/bibliographica#Cathleen_Schine" }
      } ,
      {
        "author": { "type": "uri" , "value": "http://www.connaissance.io/onto/biblio/bibliographica#Fred_Darvill" }
      } ,
      {
        "author": { "type": "uri" , "value": "http://www.connaissance.io/onto/biblio/bibliographica#Sonja_Maria_Dahl" }
      } ,
      {
        "author": { "type": "uri" , "value": "http://www.connaissance.io/onto/biblio/bibliographica#Alan_Duff" }
      } ,
      {
        "author": { "type": "uri" , "value": "http://www.connaissance.io/onto/biblio/bibliographica#Zoe_Weil" }
      } ,
      {
        "author": { "type": "uri" , "value": "http://www.connaissance.io/onto/biblio/bibliographica#Gary_Snyder" }
      } ,
      {
        "author": { "type": "uri" , "value": "http://www.connaissance.io/onto/biblio/bibliographica#Keri_Hulme" }
      } ,
      {
        "author": { "type": "uri" , "value": "http://www.connaissance.io/onto/biblio/bibliographica#Thích._Nhat_Hạnh" }
      } ,
      {
        "author": { "type": "uri" , "value": "http://www.connaissance.io/onto/biblio/bibliographica#Ivan_Doig" }
      } ,
      {
        "author": { "type": "uri" , "value": "http://www.connaissance.io/onto/biblio/bibliographica#Roddy_Doyle" }
      } ,
      {
        "author": { "type": "uri" , "value": "http://www.connaissance.io/onto/biblio/bibliographica#Jane_Rule" }
      } ,
      {
        "author": { "type": "uri" , "value": "http://www.connaissance.io/onto/biblio/bibliographica#James_Patterson" }
      } ,
      {
        "author": { "type": "uri" , "value": "http://www.connaissance.io/onto/biblio/bibliographica#Dick_Francis" }
      } ,
      {
        "author": { "type": "uri" , "value": "http://www.connaissance.io/onto/biblio/bibliographica#Mary_Oliver" }
      } ,
      {
        "author": { "type": "uri" , "value": "http://www.connaissance.io/onto/biblio/bibliographica#Mick_Goodrick" }
      } ,
      {
        "author": { "type": "uri" , "value": "http://www.connaissance.io/onto/biblio/bibliographica#Evan_S_Connell" }
      } ,
      {
        "author": { "type": "uri" , "value": "http://www.connaissance.io/onto/biblio/bibliographica#Karl_Marlantes" }
      } ,
      {
        "author": { "type": "uri" , "value": "http://www.connaissance.io/onto/biblio/bibliographica#Kathleen_Tyau" }
      } ,
      {
        "author": { "type": "uri" , "value": "http://www.connaissance.io/onto/biblio/bibliographica#Pavel_Kohout" }
      } ,
      {
        "author": { "type": "uri" , "value": "http://www.connaissance.io/onto/biblio/bibliographica#Elizabeth_Berg" }
      } ,
      {
        "author": { "type": "uri" , "value": "http://www.connaissance.io/onto/biblio/bibliographica#Leo_Tolstoy" }
      } ,
      {
        "author": { "type": "uri" , "value": "http://www.connaissance.io/onto/biblio/bibliographica#Otto_Werner" }
      } ,
      {
        "author": { "type": "uri" , "value": "http://www.connaissance.io/onto/biblio/bibliographica#Troy_Soos" }
      } ,
      {
        "author": { "type": "uri" , "value": "http://www.connaissance.io/onto/biblio/bibliographica#Pearl_Luke" }
      } ,
      {
        "author": { "type": "uri" , "value": "http://www.connaissance.io/onto/biblio/bibliographica#Robert_Boswell" }
      } ,
      {
        "author": { "type": "uri" , "value": "http://www.connaissance.io/onto/biblio/bibliographica#Robert_Olen_Butler" }
      } ,
      {
        "author": { "type": "uri" , "value": "http://www.connaissance.io/onto/biblio/bibliographica#Cormac_McCarthy" }
      } ,
      {
        "author": { "type": "uri" , "value": "http://www.connaissance.io/onto/biblio/bibliographica#Mary_Monroe" }
      } ,
      {
        "author": { "type": "uri" , "value": "http://www.connaissance.io/onto/biblio/bibliographica#Phil_Baguley" }
      } ,
      {
        "author": { "type": "uri" , "value": "http://www.connaissance.io/onto/biblio/bibliographica#Eoin_Colfer" }
      } ,
      {
        "author": { "type": "uri" , "value": "http://www.connaissance.io/onto/biblio/bibliographica#Donald_Peattie" }
      } ,
      {
        "author": { "type": "uri" , "value": "http://www.connaissance.io/onto/biblio/bibliographica#David_Stanley" }
      } ,
      {
        "author": { "type": "uri" , "value": "http://www.connaissance.io/onto/biblio/bibliographica#Aveline_Kushi" }
      } ,
      {
        "author": { "type": "uri" , "value": "http://www.connaissance.io/onto/biblio/bibliographica#Ginny_Callan" }
      } ,
      {
        "author": { "type": "uri" , "value": "http://www.connaissance.io/onto/biblio/bibliographica#Marita_Conlon-McKenna" }
      } ,
      {
        "author": { "type": "uri" , "value": "http://www.connaissance.io/onto/biblio/bibliographica#Jane_Urquhart" }
      } ,
      {
        "author": { "type": "uri" , "value": "http://www.connaissance.io/onto/biblio/bibliographica#Elliot_Perlman" }
      } ,
      {
        "author": { "type": "uri" , "value": "http://www.connaissance.io/onto/biblio/bibliographica#Richard_Kluger" }
      } ,
      {
        "author": { "type": "uri" , "value": "http://www.connaissance.io/onto/biblio/bibliographica#Carl_Forest" }
      } ,
      {
        "author": { "type": "uri" , "value": "http://www.connaissance.io/onto/biblio/bibliographica#Merrill_Gilfillan" }
      } ,
      {
        "author": { "type": "uri" , "value": "http://www.connaissance.io/onto/biblio/bibliographica#Henry_David_Thoreau" }
      } ,
      {
        "author": { "type": "uri" , "value": "http://www.connaissance.io/onto/biblio/bibliographica#Woody_Mann" }
      } ,
      {
        "author": { "type": "uri" , "value": "http://www.connaissance.io/onto/biblio/bibliographica#Forrest_Carter" }
      } ,
      {
        "author": { "type": "uri" , "value": "http://www.connaissance.io/onto/biblio/bibliographica#Mel_Bay" }
      } ,
      {
        "author": { "type": "uri" , "value": "http://www.connaissance.io/onto/biblio/bibliographica#Mark_Jacobson" }
      } ,
      {
        "author": { "type": "uri" , "value": "http://www.connaissance.io/onto/biblio/bibliographica#Alice_Hoffman" }
      } ,
      {
        "author": { "type": "uri" , "value": "http://www.connaissance.io/onto/biblio/bibliographica#Crab_Searl" }
      } ,
      {
        "author": { "type": "uri" , "value": "http://www.connaissance.io/onto/biblio/bibliographica#Angelo_Pellegrini" }
      } ,
      {
        "author": { "type": "uri" , "value": "http://www.connaissance.io/onto/biblio/bibliographica#Jean_Hewitt" }
      } ,
      {
        "author": { "type": "uri" , "value": "http://www.connaissance.io/onto/biblio/bibliographica#Kit_Knight" }
      } ,
      {
        "author": { "type": "uri" , "value": "http://www.connaissance.io/onto/biblio/bibliographica#David_Gans" }
      } ,
      {
        "author": { "type": "uri" , "value": "http://www.connaissance.io/onto/biblio/bibliographica#Paul_Bowles" }
      } ,
      {
        "author": { "type": "uri" , "value": "http://www.connaissance.io/onto/biblio/bibliographica#Cerridwen_Fallingstar" }
      } ,
      {
        "author": { "type": "uri" , "value": "http://www.connaissance.io/onto/biblio/bibliographica#Hannah_Hinchman" }
      } ,
      {
        "author": { "type": "uri" , "value": "http://www.connaissance.io/onto/biblio/bibliographica#Elson_Haas" }
      } ,
      {
        "author": { "type": "uri" , "value": "http://www.connaissance.io/onto/biblio/bibliographica#Tom_Wolfe" }
      } ,
      {
        "author": { "type": "uri" , "value": "http://www.connaissance.io/onto/biblio/bibliographica#Mickey_Spillane" }
      } ,
      {
        "author": { "type": "uri" , "value": "http://www.connaissance.io/onto/biblio/bibliographica#Ruth_Reichl" }
      } ,
      {
        "author": { "type": "uri" , "value": "http://www.connaissance.io/onto/biblio/bibliographica#Vincent_Kohler" }
      } ,
      {
        "author": { "type": "uri" , "value": "http://www.connaissance.io/onto/biblio/bibliographica#Tim_Dorsey" }
      } ,
      {
        "author": { "type": "uri" , "value": "http://www.connaissance.io/onto/biblio/bibliographica#Bill_Morris" }
      } ,
      {
        "author": { "type": "uri" , "value": "http://www.connaissance.io/onto/biblio/bibliographica#Helen_Campbell" }
      } ,
      {
        "author": { "type": "uri" , "value": "http://www.connaissance.io/onto/biblio/bibliographica#James_Ensor" }
      } ,
      {
        "author": { "type": "uri" , "value": "http://www.connaissance.io/onto/biblio/bibliographica#TS_Eliot" }
      } ,
      {
        "author": { "type": "uri" , "value": "http://www.connaissance.io/onto/biblio/bibliographica#AC_Bhaktivedanta_Swami" }
      } ,
      {
        "author": { "type": "uri" , "value": "http://www.connaissance.io/onto/biblio/bibliographica#J_Tom_Burgess" }
      } ,
      {
        "author": { "type": "uri" , "value": "http://www.connaissance.io/onto/biblio/bibliographica#Thomas_Wharton" }
      } ,
      {
        "author": { "type": "uri" , "value": "http://www.connaissance.io/onto/biblio/bibliographica#Craig_Johnson" }
      } ,
      {
        "author": { "type": "uri" , "value": "http://www.connaissance.io/onto/biblio/bibliographica#Connie_May_Fowler" }
      } ,
      {
        "author": { "type": "uri" , "value": "http://www.connaissance.io/onto/biblio/bibliographica#William_S_Burroughs" }
      } ,
      {
        "author": { "type": "uri" , "value": "http://www.connaissance.io/onto/biblio/bibliographica#Charlie_Smith" }
      } ,
      {
        "author": { "type": "uri" , "value": "http://www.connaissance.io/onto/biblio/bibliographica#Robertson_Davies" }
      } ,
      {
        "author": { "type": "uri" , "value": "http://www.connaissance.io/onto/biblio/bibliographica#Frederick_Copleston" }
      } ,
      {
        "author": { "type": "uri" , "value": "http://www.connaissance.io/onto/biblio/bibliographica#Dashka_Slater" }
      } ,
      {
        "author": { "type": "uri" , "value": "http://www.connaissance.io/onto/biblio/bibliographica#Patricia_Grace" }
      } ,
      {
        "author": { "type": "uri" , "value": "http://www.connaissance.io/onto/biblio/bibliographica#Muriel_Sweet" }
      } ,
      {
        "author": { "type": "uri" , "value": "http://www.connaissance.io/onto/biblio/bibliographica#John_Crowley" }
      } ,
      {
        "author": { "type": "uri" , "value": "http://www.connaissance.io/onto/biblio/bibliographica#Gwen_Diehn" }
      } ,
      {
        "author": { "type": "uri" , "value": "http://www.connaissance.io/onto/biblio/bibliographica#Anna_Thomas" }
      } ,
      {
        "author": { "type": "uri" , "value": "http://www.connaissance.io/onto/biblio/bibliographica#Kate_Atkinson" }
      } ,
      {
        "author": { "type": "uri" , "value": "http://www.connaissance.io/onto/biblio/bibliographica#Richard_Adams" }
      } ,
      {
        "author": { "type": "uri" , "value": "http://www.connaissance.io/onto/biblio/bibliographica#Charles_Bukowski" }
      } ,
      {
        "author": { "type": "uri" , "value": "http://www.connaissance.io/onto/biblio/bibliographica#Jessica_Maxwell" }
      } ,
      {
        "author": { "type": "uri" , "value": "http://www.connaissance.io/onto/biblio/bibliographica#Elizabeth_Arthur" }
      } ,
      {
        "author": { "type": "uri" , "value": "http://www.connaissance.io/onto/biblio/bibliographica#Junichiro_Tanizaki" }
      } ,
      {
        "author": { "type": "uri" , "value": "http://www.connaissance.io/onto/biblio/bibliographica#Sandra_Benitez" }
      } ,
      {
        "author": { "type": "uri" , "value": "http://www.connaissance.io/onto/biblio/bibliographica#Tom_Watts" }
      } ,
      {
        "author": { "type": "uri" , "value": "http://www.connaissance.io/onto/biblio/bibliographica#CS_Lewis" }
      } ,
      {
        "author": { "type": "uri" , "value": "http://www.connaissance.io/onto/biblio/bibliographica#Ken_Follett" }
      } ,
      {
        "author": { "type": "uri" , "value": "http://www.connaissance.io/onto/biblio/bibliographica#Victor_Sodsook" }
      } ,
      {
        "author": { "type": "uri" , "value": "http://www.connaissance.io/onto/biblio/bibliographica#Ardythe_Ashley" }
      } ,
      {
        "author": { "type": "uri" , "value": "http://www.connaissance.io/onto/biblio/bibliographica#Austin_Sicard" }
      } ,
      {
        "author": { "type": "uri" , "value": "http://www.connaissance.io/onto/biblio/bibliographica#Larry_Brown" }
      } ,
      {
        "author": { "type": "uri" , "value": "http://www.connaissance.io/onto/biblio/bibliographica#Deepak_Chopra" }
      } ,
      {
        "author": { "type": "uri" , "value": "http://www.connaissance.io/onto/biblio/bibliographica#David_Sibley" }
      } ,
      {
        "author": { "type": "uri" , "value": "http://www.connaissance.io/onto/biblio/bibliographica#Jill_Ker_Conway" }
      } ,
      {
        "author": { "type": "uri" , "value": "http://www.connaissance.io/onto/biblio/bibliographica#Lindsey_Davis" }
      } ,
      {
        "author": { "type": "uri" , "value": "http://www.connaissance.io/onto/biblio/bibliographica#Sharon_Pape" }
      } ,
      {
        "author": { "type": "uri" , "value": "http://www.connaissance.io/onto/biblio/bibliographica#Jiawei_Han" }
      } ,
      {
        "author": { "type": "uri" , "value": "http://www.connaissance.io/onto/biblio/bibliographica#Maxine_Hong_Kingston" }
      } ,
      {
        "author": { "type": "uri" , "value": "http://www.connaissance.io/onto/biblio/bibliographica#Norman_Rush" }
      } ,
      {
        "author": { "type": "uri" , "value": "http://www.connaissance.io/onto/biblio/bibliographica#Jean_Vaysse" }
      } ,
      {
        "author": { "type": "uri" , "value": "http://www.connaissance.io/onto/biblio/bibliographica#Charles_Baker" }
      } ,
      {
        "author": { "type": "uri" , "value": "http://www.connaissance.io/onto/biblio/bibliographica#Ottmar_Liebert" }
      } ,
      {
        "author": { "type": "uri" , "value": "http://www.connaissance.io/onto/biblio/bibliographica#Patricia_Schechter" }
      } ,
      {
        "author": { "type": "uri" , "value": "http://www.connaissance.io/onto/biblio/bibliographica#Jim_Dodge" }
      } ,
      {
        "author": { "type": "uri" , "value": "http://www.connaissance.io/onto/biblio/bibliographica#Ron_Hansen" }
      } ,
      {
        "author": { "type": "uri" , "value": "http://www.connaissance.io/onto/biblio/bibliographica#Emmett_Grogan" }
      } ,
      {
        "author": { "type": "uri" , "value": "http://www.connaissance.io/onto/biblio/bibliographica#Steven_Jenkins" }
      } ,
      {
        "author": { "type": "uri" , "value": "http://www.connaissance.io/onto/biblio/bibliographica#Julia_Alvarez" }
      } ,
      {
        "author": { "type": "uri" , "value": "http://www.connaissance.io/onto/biblio/bibliographica#Stephen_Myhre" }
      } ,
      {
        "author": { "type": "uri" , "value": "http://www.connaissance.io/onto/biblio/bibliographica#Russell_Banks" }
      } ,
      {
        "author": { "type": "uri" , "value": "http://www.connaissance.io/onto/biblio/bibliographica#James_Crumley" }
      } ,
      {
        "author": { "type": "uri" , "value": "http://www.connaissance.io/onto/biblio/bibliographica#Jana_Kolpen" }
      } ,
      {
        "author": { "type": "uri" , "value": "http://www.connaissance.io/onto/biblio/bibliographica#Lewis_Porter" }
      } ,
      {
        "author": { "type": "uri" , "value": "http://www.connaissance.io/onto/biblio/bibliographica#Grateful_Dead" }
      } ,
      {
        "author": { "type": "uri" , "value": "http://www.connaissance.io/onto/biblio/bibliographica#Jo-Ann_Mapson" }
      } ,
      {
        "author": { "type": "uri" , "value": "http://www.connaissance.io/onto/biblio/bibliographica#Robert_Gagne" }
      } ,
      {
        "author": { "type": "uri" , "value": "http://www.connaissance.io/onto/biblio/bibliographica#Rachel_Cusk" }
      } ,
      {
        "author": { "type": "uri" , "value": "http://www.connaissance.io/onto/biblio/bibliographica#Ruth_Rendell" }
      } ,
      {
        "author": { "type": "uri" , "value": "http://www.connaissance.io/onto/biblio/bibliographica#Terry_Farish" }
      } ,
      {
        "author": { "type": "uri" , "value": "http://www.connaissance.io/onto/biblio/bibliographica#Mark_Bego" }
      } ,
      {
        "author": { "type": "uri" , "value": "http://www.connaissance.io/onto/biblio/bibliographica#Per_Amann" }
      } ,
      {
        "author": { "type": "uri" , "value": "http://www.connaissance.io/onto/biblio/bibliographica#Patti_Smith" }
      } ,
      {
        "author": { "type": "uri" , "value": "http://www.connaissance.io/onto/biblio/bibliographica#Dan_OBrien" }
      } ,
      {
        "author": { "type": "uri" , "value": "http://www.connaissance.io/onto/biblio/bibliographica#Chris_Bohjalian" }
      } ,
      {
        "author": { "type": "uri" , "value": "http://www.connaissance.io/onto/biblio/bibliographica#JD_Salinger" }
      } ,
      {
        "author": { "type": "uri" , "value": "http://www.connaissance.io/onto/biblio/bibliographica#John_Steinbeck" }
      } ,
      {
        "author": { "type": "uri" , "value": "http://www.connaissance.io/onto/biblio/bibliographica#Moosewood_Collective" }
      } ,
      {
        "author": { "type": "uri" , "value": "http://www.connaissance.io/onto/biblio/bibliographica#PJ_ORourke" }
      } ,
      {
        "author": { "type": "uri" , "value": "http://www.connaissance.io/onto/biblio/bibliographica#Michael_Dibdin" }
      } ,
      {
        "author": { "type": "uri" , "value": "http://www.connaissance.io/onto/biblio/bibliographica#April_Sinclair" }
      } ,
      {
        "author": { "type": "uri" , "value": "http://www.connaissance.io/onto/biblio/bibliographica#Maryse_Conde" }
      } ,
      {
        "author": { "type": "uri" , "value": "http://www.connaissance.io/onto/biblio/bibliographica#Edward_Rice" }
      } ,
      {
        "author": { "type": "uri" , "value": "http://www.connaissance.io/onto/biblio/bibliographica#Seamus_Heaney" }
      } ,
      {
        "author": { "type": "uri" , "value": "http://www.connaissance.io/onto/biblio/bibliographica#Jim_DuFresne" }
      } ,
      {
        "author": { "type": "uri" , "value": "http://www.connaissance.io/onto/biblio/bibliographica#Nick_Bantock" }
      } ,
      {
        "author": { "type": "uri" , "value": "http://www.connaissance.io/onto/biblio/bibliographica#Daniel_Quinn" }
      } ,
      {
        "author": { "type": "uri" , "value": "http://www.connaissance.io/onto/biblio/bibliographica#Richard_Powers" }
      } ,
      {
        "author": { "type": "uri" , "value": "http://www.connaissance.io/onto/biblio/bibliographica#Frances_Moore_Lappe" }
      } ,
      {
        "author": { "type": "uri" , "value": "http://www.connaissance.io/onto/biblio/bibliographica#WP_Kinsella" }
      } ,
      {
        "author": { "type": "uri" , "value": "http://www.connaissance.io/onto/biblio/bibliographica#Kiran_Desai" }
      } ,
      {
        "author": { "type": "uri" , "value": "http://www.connaissance.io/onto/biblio/bibliographica#Mickey_Hart" }
      } ,
      {
        "author": { "type": "uri" , "value": "http://www.connaissance.io/onto/biblio/bibliographica#Michael_Kernan" }
      } ,
      {
        "author": { "type": "uri" , "value": "http://www.connaissance.io/onto/biblio/bibliographica#Jerry_Garcia" }
      } ,
      {
        "author": { "type": "uri" , "value": "http://www.connaissance.io/onto/biblio/bibliographica#Dorothy_Dunnett" }
      } ,
      {
        "author": { "type": "uri" , "value": "http://www.connaissance.io/onto/biblio/bibliographica#Dave_DeWitt" }
      } ,
      {
        "author": { "type": "uri" , "value": "http://www.connaissance.io/onto/biblio/bibliographica#Kerstin_Ekman" }
      } ,
      {
        "author": { "type": "uri" , "value": "http://www.connaissance.io/onto/biblio/bibliographica#Shunto_Aoyama" }
      } ,
      {
        "author": { "type": "uri" , "value": "http://www.connaissance.io/onto/biblio/bibliographica#Wayne_Johnson" }
      } ,
      {
        "author": { "type": "uri" , "value": "http://www.connaissance.io/onto/biblio/bibliographica#Bruce_Shlain" }
      } ,
      {
        "author": { "type": "uri" , "value": "http://www.connaissance.io/onto/biblio/bibliographica#Eliot_Asinof" }
      } ,
      {
        "author": { "type": "uri" , "value": "http://www.connaissance.io/onto/biblio/bibliographica#Lawrence_Lee" }
      } ,
      {
        "author": { "type": "uri" , "value": "http://www.connaissance.io/onto/biblio/bibliographica#Camilla_Lackberg" }
      } ,
      {
        "author": { "type": "uri" , "value": "http://www.connaissance.io/onto/biblio/bibliographica#Jostein_Gaarder" }
      } ,
      {
        "author": { "type": "uri" , "value": "http://www.connaissance.io/onto/biblio/bibliographica#JK_Rowling" }
      } ,
      {
        "author": { "type": "uri" , "value": "http://www.connaissance.io/onto/biblio/bibliographica#Van_Reid" }
      } ,
      {
        "author": { "type": "uri" , "value": "http://www.connaissance.io/onto/biblio/bibliographica#Walter_Wager" }
      } ,
      {
        "author": { "type": "uri" , "value": "http://www.connaissance.io/onto/biblio/bibliographica#Michael_Connelly" }
      } ,
      {
        "author": { "type": "uri" , "value": "http://www.connaissance.io/onto/biblio/bibliographica#James_Ellroy" }
      } ,
      {
        "author": { "type": "uri" , "value": "http://www.connaissance.io/onto/biblio/bibliographica#Kazuo_Ishiguro" }
      } ,
      {
        "author": { "type": "uri" , "value": "http://www.connaissance.io/onto/biblio/bibliographica#Robert_Kay" }
      } ,
      {
        "author": { "type": "uri" , "value": "http://www.connaissance.io/onto/biblio/bibliographica#Nicholas_Rinaldi" }
      } ,
      {
        "author": { "type": "uri" , "value": "http://www.connaissance.io/onto/biblio/bibliographica#Swain_Wolfe" }
      } ,
      {
        "author": { "type": "uri" , "value": "http://www.connaissance.io/onto/biblio/bibliographica#James_Lee_Burke" }
      } ,
      {
        "author": { "type": "uri" , "value": "http://www.connaissance.io/onto/biblio/bibliographica#Sarah_Graves" }
      } ,
      {
        "author": { "type": "uri" , "value": "http://www.connaissance.io/onto/biblio/bibliographica#Royal_Robbins" }
      } ,
      {
        "author": { "type": "uri" , "value": "http://www.connaissance.io/onto/biblio/bibliographica#Frederick_Forsyth" }
      } ,
      {
        "author": { "type": "uri" , "value": "http://www.connaissance.io/onto/biblio/bibliographica#William_Carpenter" }
      } ,
      {
        "author": { "type": "uri" , "value": "http://www.connaissance.io/onto/biblio/bibliographica#Rosario_Ferre" }
      } ,
      {
        "author": { "type": "uri" , "value": "http://www.connaissance.io/onto/biblio/bibliographica#Susan_Straight" }
      } ,
      {
        "author": { "type": "uri" , "value": "http://www.connaissance.io/onto/biblio/bibliographica#Alice_Walker" }
      } ,
      {
        "author": { "type": "uri" , "value": "http://www.connaissance.io/onto/biblio/bibliographica#Lorraine_Anderson" }
      } ,
      {
        "author": { "type": "uri" , "value": "http://www.connaissance.io/onto/biblio/bibliographica#Carl_Hiaasen" }
      } ,
      {
        "author": { "type": "uri" , "value": "http://www.connaissance.io/onto/biblio/bibliographica#Becky_Ohlsen" }
      } ,
      {
        "author": { "type": "uri" , "value": "http://www.connaissance.io/onto/biblio/bibliographica#David_Seals" }
      } ,
      {
        "author": { "type": "uri" , "value": "http://www.connaissance.io/onto/biblio/bibliographica#Garrsion_Keillor" }
      } ,
      {
        "author": { "type": "uri" , "value": "http://www.connaissance.io/onto/biblio/bibliographica#Joanne_Harris" }
      } ,
      {
        "author": { "type": "uri" , "value": "http://www.connaissance.io/onto/biblio/bibliographica#Dan_Haerle" }
      } ,
      {
        "author": { "type": "uri" , "value": "http://www.connaissance.io/onto/biblio/bibliographica#Somerville_E_Œ" }
      } ,
      {
        "author": { "type": "uri" , "value": "http://www.connaissance.io/onto/biblio/bibliographica#Elsbeth_Woody" }
      } ,
      {
        "author": { "type": "uri" , "value": "http://www.connaissance.io/onto/biblio/bibliographica#Tim_Cahill" }
      } ,
      {
        "author": { "type": "uri" , "value": "http://www.connaissance.io/onto/biblio/bibliographica#Jennifer_Egan" }
      } ,
      {
        "author": { "type": "uri" , "value": "http://www.connaissance.io/onto/biblio/bibliographica#Irma_Rombauer" }
      } ,
      {
        "author": { "type": "uri" , "value": "http://www.connaissance.io/onto/biblio/bibliographica#Scott_Meyer" }
      } ,
      {
        "author": { "type": "uri" , "value": "http://www.connaissance.io/onto/biblio/bibliographica#Clarence_Major" }
      } ,
      {
        "author": { "type": "uri" , "value": "http://www.connaissance.io/onto/biblio/bibliographica#Helen_DeWitt" }
      } ,
      {
        "author": { "type": "uri" , "value": "http://www.connaissance.io/onto/biblio/bibliographica#Heather_Cheney" }
      } ,
      {
        "author": { "type": "uri" , "value": "http://www.connaissance.io/onto/biblio/bibliographica#Louise_Erdrich" }
      } ,
      {
        "author": { "type": "uri" , "value": "http://www.connaissance.io/onto/biblio/bibliographica#Anthony_Doerr" }
      } ,
      {
        "author": { "type": "uri" , "value": "http://www.connaissance.io/onto/biblio/bibliographica#Brad_Leithauser" }
      } ,
      {
        "author": { "type": "uri" , "value": "http://www.connaissance.io/onto/biblio/bibliographica#Barry_Gifford" }
      } ,
      {
        "author": { "type": "uri" , "value": "http://www.connaissance.io/onto/biblio/bibliographica#Laurel_Robertson" }
      } ,
      {
        "author": { "type": "uri" , "value": "http://www.connaissance.io/onto/biblio/bibliographica#Richard_Brautigan" }
      } ,
      {
        "author": { "type": "uri" , "value": "http://www.connaissance.io/onto/biblio/bibliographica#Madeleine_Lengle" }
      } ,
      {
        "author": { "type": "uri" , "value": "http://www.connaissance.io/onto/biblio/bibliographica#Brooks_Hansen" }
      } ,
      {
        "author": { "type": "uri" , "value": "http://www.connaissance.io/onto/biblio/bibliographica#Sebastian_Faulks" }
      } ,
      {
        "author": { "type": "uri" , "value": "http://www.connaissance.io/onto/biblio/bibliographica#Stephen_Mitchell" }
      } ,
      {
        "author": { "type": "uri" , "value": "http://www.connaissance.io/onto/biblio/bibliographica#Nicholas_Mosley" }
      } ,
      {
        "author": { "type": "uri" , "value": "http://www.connaissance.io/onto/biblio/bibliographica#Paulo_Coelho" }
      } ,
      {
        "author": { "type": "uri" , "value": "http://www.connaissance.io/onto/biblio/bibliographica#Günter_Grass" }
      } ,
      {
        "author": { "type": "uri" , "value": "http://www.connaissance.io/onto/biblio/bibliographica#Neal_Cassady" }
      } ,
      {
        "author": { "type": "uri" , "value": "http://www.connaissance.io/onto/biblio/bibliographica#Earl_Shorris" }
      } ,
      {
        "author": { "type": "uri" , "value": "http://www.connaissance.io/onto/biblio/bibliographica#Malcolm_Cowley" }
      } ,
      {
        "author": { "type": "uri" , "value": "http://www.connaissance.io/onto/biblio/bibliographica#Anne_Kent_Rush" }
      } ,
      {
        "author": { "type": "uri" , "value": "http://www.connaissance.io/onto/biblio/bibliographica#Nel_King" }
      } ,
      {
        "author": { "type": "uri" , "value": "http://www.connaissance.io/onto/biblio/bibliographica#Anton_Chekhov" }
      } ,
      {
        "author": { "type": "uri" , "value": "http://www.connaissance.io/onto/biblio/bibliographica#Jabari_Asim" }
      } ,
      {
        "author": { "type": "uri" , "value": "http://www.connaissance.io/onto/biblio/bibliographica#J_Robert_Lennon" }
      } ,
      {
        "author": { "type": "uri" , "value": "http://www.connaissance.io/onto/biblio/bibliographica#Jingxiong_Wu" }
      } ,
      {
        "author": { "type": "uri" , "value": "http://www.connaissance.io/onto/biblio/bibliographica#Malcolm_Gladwell" }
      } ,
      {
        "author": { "type": "uri" , "value": "http://www.connaissance.io/onto/biblio/bibliographica#Gail_Anderson-Dargatz" }
      } ,
      {
        "author": { "type": "uri" , "value": "http://www.connaissance.io/onto/biblio/bibliographica#Paulette_Jiles" }
      } ,
      {
        "author": { "type": "uri" , "value": "http://www.connaissance.io/onto/biblio/bibliographica#Stieg_Larsson" }
      } ,
      {
        "author": { "type": "uri" , "value": "http://www.connaissance.io/onto/biblio/bibliographica#Michael_Palin" }
      } ,
      {
        "author": { "type": "uri" , "value": "http://www.connaissance.io/onto/biblio/bibliographica#Ayya_Khema" }
      } ,
      {
        "author": { "type": "uri" , "value": "http://www.connaissance.io/onto/biblio/bibliographica#Franco_Ferrero" }
      } ,
      {
        "author": { "type": "uri" , "value": "http://www.connaissance.io/onto/biblio/bibliographica#Sunetra_Gupta" }
      } ,
      {
        "author": { "type": "uri" , "value": "http://www.connaissance.io/onto/biblio/bibliographica#Al_Di_Meola" }
      } ,
      {
        "author": { "type": "uri" , "value": "http://www.connaissance.io/onto/biblio/bibliographica#Arundhati_Roy" }
      } ,
      {
        "author": { "type": "uri" , "value": "http://www.connaissance.io/onto/biblio/bibliographica#Brett_Helquist" }
      } ,
      {
        "author": { "type": "uri" , "value": "http://www.connaissance.io/onto/biblio/bibliographica#Jean_Zallinger" }
      } ,
      {
        "author": { "type": "uri" , "value": "http://www.connaissance.io/onto/biblio/bibliographica#Jorge_Amado" }
      } ,
      {
        "author": { "type": "uri" , "value": "http://www.connaissance.io/onto/biblio/bibliographica#SE_Hinton" }
      } ,
      {
        "author": { "type": "uri" , "value": "http://www.connaissance.io/onto/biblio/bibliographica#John_Brimhall" }
      } ,
      {
        "author": { "type": "uri" , "value": "http://www.connaissance.io/onto/biblio/bibliographica#Gilbert_Shelton" }
      } ,
      {
        "author": { "type": "uri" , "value": "http://www.connaissance.io/onto/biblio/bibliographica#Floyd_Shuttleworth" }
      } ,
      {
        "author": { "type": "uri" , "value": "http://www.connaissance.io/onto/biblio/bibliographica#Zora_Neale_Hurston" }
      } ,
      {
        "author": { "type": "uri" , "value": "http://www.connaissance.io/onto/biblio/bibliographica#Audrey_Niffenegger" }
      } ,
      {
        "author": { "type": "uri" , "value": "http://www.connaissance.io/onto/biblio/bibliographica#Derek_Hansen" }
      } ,
      {
        "author": { "type": "uri" , "value": "http://www.connaissance.io/onto/biblio/bibliographica#Albert_Einstein" }
      } ,
      {
        "author": { "type": "uri" , "value": "http://www.connaissance.io/onto/biblio/bibliographica#Carl_Bode" }
      } ,
      {
        "author": { "type": "uri" , "value": "http://www.connaissance.io/onto/biblio/bibliographica#Susan_Fox_Rogers" }
      } ,
      {
        "author": { "type": "uri" , "value": "http://www.connaissance.io/onto/biblio/bibliographica#Martin_Lee" }
      } ,
      {
        "author": { "type": "uri" , "value": "http://www.connaissance.io/onto/biblio/bibliographica#Harold_McGee" }
      } ,
      {
        "author": { "type": "uri" , "value": "http://www.connaissance.io/onto/biblio/bibliographica#Beatles" }
      } ,
      {
        "author": { "type": "uri" , "value": "http://www.connaissance.io/onto/biblio/bibliographica#Mil_Millington" }
      } ,
      {
        "author": { "type": "uri" , "value": "http://www.connaissance.io/onto/biblio/bibliographica#Paul_Auster" }
      } ,
      {
        "author": { "type": "uri" , "value": "http://www.connaissance.io/onto/biblio/bibliographica#Tananarive_Due" }
      } ,
      {
        "author": { "type": "uri" , "value": "http://www.connaissance.io/onto/biblio/bibliographica#Adriana_Trigiani" }
      } ,
      {
        "author": { "type": "uri" , "value": "http://www.connaissance.io/onto/biblio/bibliographica#ER_LaChapelle" }
      } ,
      {
        "author": { "type": "uri" , "value": "http://www.connaissance.io/onto/biblio/bibliographica#Ralph_Steadman" }
      } ,
      {
        "author": { "type": "uri" , "value": "http://www.connaissance.io/onto/biblio/bibliographica#David_James_Duncan" }
      } ,
      {
        "author": { "type": "uri" , "value": "http://www.connaissance.io/onto/biblio/bibliographica#Kathy_Eldon" }
      } ,
      {
        "author": { "type": "uri" , "value": "http://www.connaissance.io/onto/biblio/bibliographica#Schuyler_Ingle" }
      } ,
      {
        "author": { "type": "uri" , "value": "http://www.connaissance.io/onto/biblio/bibliographica#Madhur_Jaffrey" }
      } ,
      {
        "author": { "type": "uri" , "value": "http://www.connaissance.io/onto/biblio/bibliographica#Kenneth_Patchen" }
      } ,
      {
        "author": { "type": "uri" , "value": "http://www.connaissance.io/onto/biblio/bibliographica#Stephen_Dobyns" }
      } ,
      {
        "author": { "type": "uri" , "value": "http://www.connaissance.io/onto/biblio/bibliographica#Brian_Moore" }
      } ,
      {
        "author": { "type": "uri" , "value": "http://www.connaissance.io/onto/biblio/bibliographica#James_McBride" }
      } ,
      {
        "author": { "type": "uri" , "value": "http://www.connaissance.io/onto/biblio/bibliographica#James_Kelman" }
      } ,
      {
        "author": { "type": "uri" , "value": "http://www.connaissance.io/onto/biblio/bibliographica#Danny_Elfman" }
      } ,
      {
        "author": { "type": "uri" , "value": "http://www.connaissance.io/onto/biblio/bibliographica#JRH_Andrews" }
      } ,
      {
        "author": { "type": "uri" , "value": "http://www.connaissance.io/onto/biblio/bibliographica#Peter_Carey" }
      } ,
      {
        "author": { "type": "uri" , "value": "http://www.connaissance.io/onto/biblio/bibliographica#Yamaha" }
      } ,
      {
        "author": { "type": "uri" , "value": "http://www.connaissance.io/onto/biblio/bibliographica#Rudolfo_Anaya" }
      } ,
      {
        "author": { "type": "uri" , "value": "http://www.connaissance.io/onto/biblio/bibliographica#PD_James" }
      } ,
      {
        "author": { "type": "uri" , "value": "http://www.connaissance.io/onto/biblio/bibliographica#John_Lescroart" }
      } ,
      {
        "author": { "type": "uri" , "value": "http://www.connaissance.io/onto/biblio/bibliographica#Kiana_Davenport" }
      } ,
      {
        "author": { "type": "uri" , "value": "http://www.connaissance.io/onto/biblio/bibliographica#Miles_Davis" }
      } ,
      {
        "author": { "type": "uri" , "value": "http://www.connaissance.io/onto/biblio/bibliographica#Carol_Brightman" }
      }
    ]
  }
}
